pyguiEZ/__init__.py
pyguiEZ/app.py
pyguiEZ/button.py
pyguiEZ/label.py
pyguiez-0.1.0.dist-info/METADATA
pyguiez-0.1.0.dist-info/WHEEL
pyguiez-0.1.0.dist-info/RECORD
